nonebot_plugin_setu_collection/__init__.py
nonebot_plugin_setu_collection/config.py
nonebot_plugin_setu_collection-0.4.0.post3.dist-info/LICENSE
nonebot_plugin_setu_collection-0.4.0.post3.dist-info/METADATA
nonebot_plugin_setu_collection-0.4.0.post3.dist-info/WHEEL
nonebot_plugin_setu_collection-0.4.0.post3.dist-info/RECORD
